lazr.restful-2.0.3-py3.13-nspkg.pth
lazr/restful/__init__.py
lazr/restful/_bytestorage.py
lazr/restful/_operation.py
lazr/restful/_resource.py
lazr/restful/basic-site.zcml
lazr/restful/configure.zcml
lazr/restful/debug.py
lazr/restful/declarations.py
lazr/restful/error.py
lazr/restful/fields.py
lazr/restful/ftesting.zcml
lazr/restful/interface.py
lazr/restful/jsoncache.py
lazr/restful/marshallers.py
lazr/restful/meta.zcml
lazr/restful/metazcml.py
lazr/restful/publisher.py
lazr/restful/security.py
lazr/restful/simple.py
lazr/restful/tales.py
lazr/restful/utils.py
lazr/restful/wadl20061109.xsd
lazr/restful/wsgi.py
lazr/restful/directives/__init__.py
lazr/restful/docs/CONTRIBUTING.rst
lazr/restful/docs/Makefile
lazr/restful/docs/NEWS.rst
lazr/restful/docs/__init__.py
lazr/restful/docs/absoluteurl.rst
lazr/restful/docs/checker-utilities.rst
lazr/restful/docs/conf.py
lazr/restful/docs/debug.rst
lazr/restful/docs/django.rst
lazr/restful/docs/fields.rst
lazr/restful/docs/index.rst
lazr/restful/docs/interface.rst
lazr/restful/docs/multiversion.rst
lazr/restful/docs/utils.rst
lazr/restful/docs/webservice-declarations.rst
lazr/restful/docs/webservice-error.rst
lazr/restful/docs/webservice-marshallers.rst
lazr/restful/docs/webservice-request.rst
lazr/restful/docs/webservice.rst
lazr/restful/example/__init__.py
lazr/restful/example/base/__init__.py
lazr/restful/example/base/configure.zcml
lazr/restful/example/base/filemanager.py
lazr/restful/example/base/interfaces.py
lazr/restful/example/base/root.py
lazr/restful/example/base/security.py
lazr/restful/example/base/subscribers.py
lazr/restful/example/base/traversal.py
lazr/restful/example/base/tests/__init__.py
lazr/restful/example/base/tests/collection.txt
lazr/restful/example/base/tests/entry.txt
lazr/restful/example/base/tests/field.txt
lazr/restful/example/base/tests/hostedfile.txt
lazr/restful/example/base/tests/redirect.txt
lazr/restful/example/base/tests/representation-cache.txt
lazr/restful/example/base/tests/root.txt
lazr.restful-2.0.3.dist-info/COPYING.txt
lazr.restful-2.0.3.dist-info/METADATA
lazr.restful-2.0.3.dist-info/WHEEL
lazr.restful-2.0.3.dist-info/namespace_packages.txt
lazr.restful-2.0.3.dist-info/top_level.txt
lazr.restful-2.0.3.dist-info/RECORD
