Metadata-Version: 2.1
Name: lazr.restful
Version: 2.0.3
Summary: Publish Python objects as RESTful resources over HTTP.
Home-page: https://launchpad.net/lazr.restful
Download-URL: https://launchpad.net/lazr.restful/+download
Maintainer: LAZR Developers
Maintainer-email: lazr-developers@lists.launchpad.net
License: LGPL v3
Classifier: Development Status :: 5 - Production/Stable
Classifier: Intended Audience :: Developers
Classifier: License :: OSI Approved :: GNU Library or Lesser General Public License (LGPL)
Classifier: Operating System :: OS Independent
Classifier: Programming Language :: Python
Classifier: Programming Language :: Python :: 3
Classifier: Programming Language :: Python :: 3.8
Classifier: Programming Language :: Python :: 3.9
Classifier: Programming Language :: Python :: 3.10
Classifier: Programming Language :: Python :: 3.11
Classifier: Programming Language :: Python :: 3.12
Classifier: Programming Language :: Python :: 3.13
Requires-Python: >=3.8
License-File: COPYING.txt
Requires-Dist: docutils>=0.3.9
Requires-Dist: grokcore.component>=1.6
Requires-Dist: lazr.batchnavigator>=1.2.0-dev
Requires-Dist: lazr.delegates>=2.0.3
Requires-Dist: lazr.enum
Requires-Dist: lazr.lifecycle
Requires-Dist: lazr.uri
Requires-Dist: martian>=0.11
Requires-Dist: pytz
Requires-Dist: setuptools
Requires-Dist: testtools
Requires-Dist: van.testing
Requires-Dist: zope.component[zcml]
Requires-Dist: zope.configuration
Requires-Dist: zope.datetime
Requires-Dist: zope.event
Requires-Dist: zope.interface>=3.8.0
Requires-Dist: zope.pagetemplate
Requires-Dist: zope.processlifetime
Requires-Dist: zope.proxy
Requires-Dist: zope.publisher>=6.0.0
Requires-Dist: zope.schema
Requires-Dist: zope.security
Requires-Dist: zope.traversing
Provides-Extra: docs
Requires-Dist: Sphinx; extra == "docs"
Provides-Extra: test
Requires-Dist: zope.testing>=4.6.0; extra == "test"
Requires-Dist: zope.testrunner>=6.6.1; extra == "test"
Provides-Extra: xml
Requires-Dist: lxml; extra == "xml"
